README.txt
setup.py
xlsrch/__init__.py
xlsrch/__main__.py
xlsrch/xlsrch.py
xlsrch.egg-info/PKG-INFO
xlsrch.egg-info/SOURCES.txt
xlsrch.egg-info/dependency_links.txt
xlsrch.egg-info/requires.txt
xlsrch.egg-info/top_level.txt