Metadata-Version: 1.1
Name: xlsrch
Version: 0.0.6
Summary: tools you can search text words from MS-Excel files.
Home-page: https://anad.site/
Author: dais.cns@gmail.com
Author-email: dais.cns@gmail.com
License: MIT
Keywords: tools develop coding
Platform: UNKNOWN
Classifier: Intended Audience :: Developers
Classifier: Intended Audience :: End Users/Desktop
Classifier: Intended Audience :: Information Technology
Classifier: Intended Audience :: Science/Research
Classifier: Intended Audience :: System Administrators
Classifier: Programming Language :: Python :: 3.5
